zookeeper_locks/__init__.py
zookeeper_locks/apps.py
zookeeper_locks/locks.py
django_zk_locks-0.0.1.dist-info/LICENSE
django_zk_locks-0.0.1.dist-info/METADATA
django_zk_locks-0.0.1.dist-info/WHEEL
django_zk_locks-0.0.1.dist-info/top_level.txt
django_zk_locks-0.0.1.dist-info/RECORD
