Metadata-Version: 2.1
Name: django-zk-locks
Version: 0.0.1
Summary: Distributed locks for Django using Zookeeper.
Home-page: https://github.com/DDuarte/django-zk-locks
Download-URL: https://pypi.org/project/django-zk-locks/
Author: Duarte Duarte
Author-email: dnpd.dd@gmail.com
License: BSD
Classifier: Development Status :: 5 - Production/Stable
Classifier: Environment :: Web Environment
Classifier: Framework :: Django
Classifier: Framework :: Django :: 4.2
Classifier: Framework :: Django :: 5.0
Classifier: Intended Audience :: Developers
Classifier: License :: OSI Approved :: BSD License
Classifier: Operating System :: OS Independent
Classifier: Programming Language :: Python
Classifier: Programming Language :: Python :: 3
Classifier: Programming Language :: Python :: 3 :: Only
Classifier: Programming Language :: Python :: 3.10
Classifier: Topic :: Software Development :: Libraries :: Python Modules
Requires-Python: >=3.10
License-File: LICENSE
Requires-Dist: Django <6,>=4.2
Requires-Dist: kazoo >=2.10.0
